ccs_aws/__init__.py
ccs_aws/dynamo.py
ccs_aws/s3.py
ccs_aws/secrets.py
ccs_aws-2.3.2.dist-info/METADATA
ccs_aws-2.3.2.dist-info/WHEEL
ccs_aws-2.3.2.dist-info/top_level.txt
ccs_aws-2.3.2.dist-info/RECORD
