Metadata-Version: 2.1
Name: ccs-aws
Version: 2.3.2
Summary: ccs aws modules
Home-page: UNKNOWN
Author: code_duck
License: UNKNOWN
Platform: UNKNOWN
Classifier: Programming Language :: Python :: 3
Classifier: License :: OSI Approved :: MIT License
Classifier: Operating System :: OS Independent
Requires-Dist: boto3
